{
  "config": "{\"version\":\"5.59\",\"themeCollection\":{\"baseTheme\":{\"name\":\"CY24SU10\",\"version\":\"5.61\",\"type\":2}},\"activeSectionIndex\":0,\"defaultDrillFilterOtherVisuals\":true,\"slowDataSourceSettings\":{\"isCrossHighlightingDisabled\":false,\"isSlicerSelectionsButtonEnabled\":false,\"isFilterSelectionsButtonEnabled\":false,\"isFieldWellButtonEnabled\":false,\"isApplyAllButtonEnabled\":false},\"linguisticSchemaSyncVersion\":2,\"settings\":{\"useNewFilterPaneExperience\":true,\"allowChangeFilterTypes\":true,\"useStylableVisualContainerHeader\":true,\"queryLimitOption\":6,\"exportDataMode\":1,\"useDefaultAggregateDisplayName\":true,\"useEnhancedTooltips\":true,\"filterPaneHiddenInEditMode\":false},\"objects\":{\"section\":[{\"properties\":{\"verticalAlignment\":{\"expr\":{\"Literal\":{\"Value\":\"'Top'\"}}}}}],\"outspacePane\":[{\"properties\":{\"expanded\":{\"expr\":{\"Literal\":{\"Value\":\"true\"}}},\"visible\":{\"expr\":{\"Literal\":{\"Value\":\"true\"}}}}}]}}",
  "layoutOptimization": 0,
  "resourcePackages": [
    {
      "resourcePackage": {
        "disabled": false,
        "items": [
          {
            "name": "CY24SU10",
            "path": "BaseThemes/CY24SU10.json",
            "type": 202
          }
        ],
        "name": "SharedResources",
        "type": 2
      }
    }
  ],
  "sections": [
    {
      "config": "{}",
      "displayName": "Gender",
      "displayOption": 1,
      "filters": "[]",
      "height": 720.00,
      "name": "27243e3cd808369c00c2",
      "ordinal": 2,
      "visualContainers": [
        {
          "config": "{\"name\":\"0e6456933ac00a4e1b90\",\"layouts\":[{\"id\":0,\"position\":{\"x\":850.9337159253945,\"y\":31.341941654710666,\"z\":5000,\"width\":419.9820181731229,\"height\":327.5232902917264,\"tabOrder\":5000}}],\"singleVisual\":{\"visualType\":\"scatterChart\",\"projections\":{\"X\":[{\"queryRef\":\"Measure Table.Gender Ratio (F/M)\",\"active\":true}],\"Y\":[{\"queryRef\":\"Measure Table.Percentage of Hispanics\"}],\"Category\":[{\"queryRef\":\"US Demographics 2023.state\",\"active\":true}]},\"prototypeQuery\":{\"Version\":2,\"From\":[{\"Name\":\"m\",\"Entity\":\"Measure Table\",\"Type\":0},{\"Name\":\"u\",\"Entity\":\"US Demographics 2023\",\"Type\":0}],\"Select\":[{\"Measure\":{\"Expression\":{\"SourceRef\":{\"Source\":\"m\"}},\"Property\":\"Gender Ratio (F/M)\"},\"Name\":\"Measure Table.Gender Ratio (F/M)\",\"NativeReferenceName\":\"Gender Ratio (F/M)\"},{\"Measure\":{\"Expression\":{\"SourceRef\":{\"Source\":\"m\"}},\"Property\":\"Percentage Hispanics\"},\"Name\":\"Measure Table.Percentage of Hispanics\",\"NativeReferenceName\":\"Percentage of Hispanics\"},{\"Column\":{\"Expression\":{\"SourceRef\":{\"Source\":\"u\"}},\"Property\":\"state\"},\"Name\":\"US Demographics 2023.state\",\"NativeReferenceName\":\"state\"}]},\"drillFilterOtherVisuals\":true,\"objects\":{\"trend\":[{\"properties\":{\"show\":{\"expr\":{\"Literal\":{\"Value\":\"true\"}}},\"displayName\":{\"expr\":{\"Literal\":{\"Value\":\"'Trend line 1'\"}}}}}],\"dataPoint\":[{\"properties\":{\"fill\":{\"solid\":{\"color\":{\"expr\":{\"ThemeDataColor\":{\"ColorId\":4,\"Percent\":0}}}}}}}],\"categoryLabels\":[{\"properties\":{\"show\":{\"expr\":{\"Literal\":{\"Value\":\"true\"}}}}}],\"xAxisReferenceLine\":[{\"properties\":{\"show\":{\"expr\":{\"Literal\":{\"Value\":\"true\"}}},\"displayName\":{\"expr\":{\"Literal\":{\"Value\":\"'Parity'\"}}},\"value\":{\"expr\":{\"Literal\":{\"Value\":\"1D\"}}},\"dataLabelShow\":{\"expr\":{\"Literal\":{\"Value\":\"true\"}}},\"dataLabelText\":{\"expr\":{\"Literal\":{\"Value\":\"'ValueAndName'\"}}}},\"selector\":{\"id\":\"1\"}}]},\"vcObjects\":{\"title\":[{\"properties\":{\"text\":{\"expr\":{\"Literal\":{\"Value\":\"'Gender Ratio (F/M) and Percentage Hispanics by state (without Puerto Rico)'\"}}}}}]}}}",
          "filters": "[{\"name\":\"eb544563cd93701bb86d\",\"expression\":{\"Column\":{\"Expression\":{\"SourceRef\":{\"Entity\":\"US Demographics 2023\"}},\"Property\":\"state\"}},\"filter\":{\"Version\":2,\"From\":[{\"Name\":\"u\",\"Entity\":\"US Demographics 2023\",\"Type\":0}],\"Where\":[{\"Condition\":{\"Not\":{\"Expression\":{\"In\":{\"Expressions\":[{\"Column\":{\"Expression\":{\"SourceRef\":{\"Source\":\"u\"}},\"Property\":\"state\"}}],\"Values\":[[{\"Literal\":{\"Value\":\"'Puerto Rico'\"}}]]}}}}}]},\"type\":\"Categorical\",\"howCreated\":0,\"objects\":{\"general\":[{\"properties\":{\"isInvertedSelectionMode\":{\"expr\":{\"Literal\":{\"Value\":\"true\"}}}}}]},\"isHiddenInViewMode\":false}]",
          "height": 327.52,
          "width": 419.98,
          "x": 850.93,
          "y": 31.34,
          "z": 5000.00
        },
        {
          "config": "{\"name\":\"35664c2fdab0d524039e\",\"layouts\":[{\"id\":0,\"position\":{\"x\":457.5923481587757,\"y\":31.341941654710666,\"z\":4000,\"width\":393.3413677666188,\"height\":327.5232902917264,\"tabOrder\":4000}}],\"singleVisual\":{\"visualType\":\"scatterChart\",\"projections\":{\"Category\":[{\"queryRef\":\"US Demographics 2023.state\",\"active\":true}],\"X\":[{\"queryRef\":\"Measure Table.Gender Ratio (F/M)\",\"active\":true}],\"Y\":[{\"queryRef\":\"Measure Table.Percentage of Black\"}]},\"prototypeQuery\":{\"Version\":2,\"From\":[{\"Name\":\"u\",\"Entity\":\"US Demographics 2023\",\"Type\":0},{\"Name\":\"m\",\"Entity\":\"Measure Table\",\"Type\":0}],\"Select\":[{\"Column\":{\"Expression\":{\"SourceRef\":{\"Source\":\"u\"}},\"Property\":\"state\"},\"Name\":\"US Demographics 2023.state\",\"NativeReferenceName\":\"state\"},{\"Measure\":{\"Expression\":{\"SourceRef\":{\"Source\":\"m\"}},\"Property\":\"Gender Ratio (F/M)\"},\"Name\":\"Measure Table.Gender Ratio (F/M)\",\"NativeReferenceName\":\"Gender Ratio (F/M)\"},{\"Measure\":{\"Expression\":{\"SourceRef\":{\"Source\":\"m\"}},\"Property\":\"Percentage Black\"},\"Name\":\"Measure Table.Percentage of Black\",\"NativeReferenceName\":\"Percentage of Black\"}]},\"drillFilterOtherVisuals\":true,\"objects\":{\"dataPoint\":[{\"properties\":{\"fill\":{\"solid\":{\"color\":{\"expr\":{\"ThemeDataColor\":{\"ColorId\":1,\"Percent\":0.4}}}}}}}],\"categoryLabels\":[{\"properties\":{\"show\":{\"expr\":{\"Literal\":{\"Value\":\"true\"}}}}}],\"trend\":[{\"properties\":{\"show\":{\"expr\":{\"Literal\":{\"Value\":\"true\"}}},\"displayName\":{\"expr\":{\"Literal\":{\"Value\":\"'Trend line 1'\"}}}}}],\"xAxisReferenceLine\":[{\"properties\":{\"show\":{\"expr\":{\"Literal\":{\"Value\":\"true\"}}},\"displayName\":{\"expr\":{\"Literal\":{\"Value\":\"'Parity'\"}}},\"value\":{\"expr\":{\"Literal\":{\"Value\":\"1D\"}}},\"transparency\":{\"expr\":{\"Literal\":{\"Value\":\"50D\"}}},\"dataLabelShow\":{\"expr\":{\"Literal\":{\"Value\":\"true\"}}},\"dataLabelText\":{\"expr\":{\"Literal\":{\"Value\":\"'ValueAndName'\"}}}},\"selector\":{\"id\":\"1\"}}]}}}",
          "filters": "[]",
          "height": 327.52,
          "width": 393.34,
          "x": 457.59,
          "y": 31.34,
          "z": 4000.00
        },
        {
          "config": "{\"name\":\"44c3bea9716055854e02\",\"layouts\":[{\"id\":0,\"position\":{\"x\":1093.6571801872728,\"y\":481.64826881522305,\"z\":5002,\"width\":150.94390190790466,\"height\":141.33838087740165,\"tabOrder\":5002}}],\"singleVisual\":{\"visualType\":\"multiRowCard\",\"projections\":{\"Values\":[{\"queryRef\":\"Measure Table.% Black in All US\"},{\"queryRef\":\"Measure Table.% Hispanics in US\"}]},\"prototypeQuery\":{\"Version\":2,\"From\":[{\"Name\":\"m\",\"Entity\":\"Measure Table\",\"Type\":0}],\"Select\":[{\"Measure\":{\"Expression\":{\"SourceRef\":{\"Source\":\"m\"}},\"Property\":\"% Black in All US\"},\"Name\":\"Measure Table.% Black in All US\",\"NativeReferenceName\":\"% Black in All US\"},{\"Measure\":{\"Expression\":{\"SourceRef\":{\"Source\":\"m\"}},\"Property\":\"% Hispanics in US\"},\"Name\":\"Measure Table.% Hispanics in US\",\"NativeReferenceName\":\"% Hispanics in US\"}],\"OrderBy\":[{\"Direction\":2,\"Expression\":{\"Measure\":{\"Expression\":{\"SourceRef\":{\"Source\":\"m\"}},\"Property\":\"% Black in All US\"}}}]},\"drillFilterOtherVisuals\":true,\"hasDefaultSort\":true,\"objects\":{\"dataLabels\":[{\"properties\":{\"fontSize\":{\"expr\":{\"Literal\":{\"Value\":\"20D\"}}}}}]}}}",
          "filters": "[]",
          "height": 141.34,
          "width": 150.94,
          "x": 1093.66,
          "y": 481.65,
          "z": 5002.00
        },
        {
          "config": "{\"name\":\"46b87131063f5e354574\",\"layouts\":[{\"id\":0,\"position\":{\"x\":32.93321496172465,\"y\":461.06500946414513,\"z\":3000,\"width\":448.71505385349843,\"height\":259.34906782358166,\"tabOrder\":3000}}],\"singleVisual\":{\"visualType\":\"pivotTable\",\"projections\":{\"Values\":[{\"queryRef\":\"Measure Table.Gender Ratio (F/M)\"},{\"queryRef\":\"Measure Table.Total Female\"},{\"queryRef\":\"Measure Table.Total Male\"}],\"Rows\":[{\"queryRef\":\"public us_demographics_data_2023.state Hierarchy.state\",\"active\":true},{\"queryRef\":\"public us_demographics_data_2023.state Hierarchy.county\"}]},\"prototypeQuery\":{\"Version\":2,\"From\":[{\"Name\":\"m\",\"Entity\":\"Measure Table\",\"Type\":0},{\"Name\":\"p\",\"Entity\":\"US Demographics 2023\",\"Type\":0}],\"Select\":[{\"Measure\":{\"Expression\":{\"SourceRef\":{\"Source\":\"m\"}},\"Property\":\"Gender Ratio (F/M)\"},\"Name\":\"Measure Table.Gender Ratio (F/M)\",\"NativeReferenceName\":\"Gender Ratio (F/M)\"},{\"HierarchyLevel\":{\"Expression\":{\"Hierarchy\":{\"Expression\":{\"SourceRef\":{\"Source\":\"p\"}},\"Hierarchy\":\"state Hierarchy\"}},\"Level\":\"state\"},\"Name\":\"public us_demographics_data_2023.state Hierarchy.state\",\"NativeReferenceName\":\"state Hierarchy state\"},{\"HierarchyLevel\":{\"Expression\":{\"Hierarchy\":{\"Expression\":{\"SourceRef\":{\"Source\":\"p\"}},\"Hierarchy\":\"state Hierarchy\"}},\"Level\":\"county\"},\"Name\":\"public us_demographics_data_2023.state Hierarchy.county\",\"NativeReferenceName\":\"state Hierarchy county\"},{\"Measure\":{\"Expression\":{\"SourceRef\":{\"Source\":\"m\"}},\"Property\":\"Total Female\"},\"Name\":\"Measure Table.Total Female\",\"NativeReferenceName\":\"Total Female\"},{\"Measure\":{\"Expression\":{\"SourceRef\":{\"Source\":\"m\"}},\"Property\":\"Total Male\"},\"Name\":\"Measure Table.Total Male\",\"NativeReferenceName\":\"Total Male\"}],\"OrderBy\":[{\"Direction\":1,\"Expression\":{\"Measure\":{\"Expression\":{\"SourceRef\":{\"Source\":\"m\"}},\"Property\":\"Gender Ratio (F/M)\"}}}]},\"expansionStates\":[{\"roles\":[\"Rows\"],\"levels\":[{\"queryRefs\":[\"public us_demographics_data_2023.state Hierarchy.state\"],\"isCollapsed\":true,\"isPinned\":true},{\"queryRefs\":[\"public us_demographics_data_2023.state Hierarchy.county\"],\"isCollapsed\":true}],\"root\":{\"identityValues\":null}}],\"drillFilterOtherVisuals\":true}}",
          "filters": "[]",
          "height": 259.35,
          "width": 448.72,
          "x": 32.93,
          "y": 461.07,
          "z": 3000.00
        },
        {
          "config": "{\"name\":\"8af0b0267079b786030b\",\"layouts\":[{\"id\":0,\"position\":{\"x\":532.4203085478819,\"y\":384.220841220121,\"z\":5001,\"width\":561.236871639391,\"height\":336.1932360676058,\"tabOrder\":5001}}],\"singleVisual\":{\"visualType\":\"lineClusteredColumnComboChart\",\"projections\":{\"Category\":[{\"queryRef\":\"US Demographics 2023.state\",\"active\":true}],\"Y\":[{\"queryRef\":\"Measure Table.Percentage Black\"},{\"queryRef\":\"Measure Table.Percentage Hispanics\"}],\"Y2\":[{\"queryRef\":\"Measure Table.Gender Ratio (F/M)\"}]},\"prototypeQuery\":{\"Version\":2,\"From\":[{\"Name\":\"m\",\"Entity\":\"Measure Table\",\"Type\":0},{\"Name\":\"u\",\"Entity\":\"US Demographics 2023\",\"Type\":0}],\"Select\":[{\"Column\":{\"Expression\":{\"SourceRef\":{\"Source\":\"u\"}},\"Property\":\"state\"},\"Name\":\"US Demographics 2023.state\",\"NativeReferenceName\":\"state\"},{\"Measure\":{\"Expression\":{\"SourceRef\":{\"Source\":\"m\"}},\"Property\":\"Percentage Black\"},\"Name\":\"Measure Table.Percentage Black\",\"NativeReferenceName\":\"Percentage Black\"},{\"Measure\":{\"Expression\":{\"SourceRef\":{\"Source\":\"m\"}},\"Property\":\"Percentage Hispanics\"},\"Name\":\"Measure Table.Percentage Hispanics\",\"NativeReferenceName\":\"Percentage Hispanics\"},{\"Measure\":{\"Expression\":{\"SourceRef\":{\"Source\":\"m\"}},\"Property\":\"Gender Ratio (F/M)\"},\"Name\":\"Measure Table.Gender Ratio (F/M)\",\"NativeReferenceName\":\"Gender Ratio (F/M)\"}],\"OrderBy\":[{\"Direction\":1,\"Expression\":{\"Measure\":{\"Expression\":{\"SourceRef\":{\"Source\":\"m\"}},\"Property\":\"Gender Ratio (F/M)\"}}}]},\"drillFilterOtherVisuals\":true,\"objects\":{\"dataPoint\":[{\"properties\":{\"fill\":{\"solid\":{\"color\":{\"expr\":{\"ThemeDataColor\":{\"ColorId\":1,\"Percent\":0.4}}}}},\"fillTransparency\":{\"expr\":{\"Literal\":{\"Value\":\"10D\"}}}},\"selector\":{\"metadata\":\"Measure Table.Percentage Black\"}},{\"properties\":{\"fill\":{\"solid\":{\"color\":{\"expr\":{\"ThemeDataColor\":{\"ColorId\":4,\"Percent\":0}}}}},\"fillTransparency\":{\"expr\":{\"Literal\":{\"Value\":\"10D\"}}}},\"selector\":{\"metadata\":\"Measure Table.Percentage Hispanics\"}},{\"properties\":{\"fill\":{\"solid\":{\"color\":{\"expr\":{\"ThemeDataColor\":{\"ColorId\":2,\"Percent\":0}}}}}},\"selector\":{\"metadata\":\"Measure Table.Gender Ratio (F/M)\"}}]},\"vcObjects\":{\"title\":[{\"properties\":{\"text\":{\"expr\":{\"Literal\":{\"Value\":\"'% Black and % Hispanics of 15 States with Lowest Gender Ratio (F/M)'\"}}}}}]}}}",
          "filters": "[{\"expression\":{\"Column\":{\"Expression\":{\"SourceRef\":{\"Entity\":\"US Demographics 2023\"}},\"Property\":\"state\"}},\"filter\":{\"Version\":2,\"From\":[{\"Name\":\"subquery\",\"Expression\":{\"Subquery\":{\"Query\":{\"Version\":2,\"From\":[{\"Name\":\"u\",\"Entity\":\"US Demographics 2023\",\"Type\":0},{\"Name\":\"m\",\"Entity\":\"Measure Table\",\"Type\":0}],\"Select\":[{\"Column\":{\"Expression\":{\"SourceRef\":{\"Source\":\"u\"}},\"Property\":\"state\"},\"Name\":\"field\"}],\"OrderBy\":[{\"Direction\":1,\"Expression\":{\"Measure\":{\"Expression\":{\"SourceRef\":{\"Source\":\"m\"}},\"Property\":\"Gender Ratio (F/M)\"}}}],\"Top\":15}}},\"Type\":2},{\"Name\":\"u\",\"Entity\":\"US Demographics 2023\",\"Type\":0}],\"Where\":[{\"Condition\":{\"In\":{\"Expressions\":[{\"Column\":{\"Expression\":{\"SourceRef\":{\"Source\":\"u\"}},\"Property\":\"state\"}}],\"Table\":{\"SourceRef\":{\"Source\":\"subquery\"}}}}}]},\"type\":\"TopN\",\"howCreated\":0,\"isHiddenInViewMode\":false}]",
          "height": 336.19,
          "width": 561.24,
          "x": 532.42,
          "y": 384.22,
          "z": 5001.00
        },
        {
          "config": "{\"name\":\"be706a4feb0549c9c175\",\"layouts\":[{\"id\":0,\"position\":{\"x\":104.2885140454614,\"y\":359.52092999882746,\"z\":1000,\"width\":141.33838087740165,\"height\":101.54407946531768,\"tabOrder\":1000}}],\"singleVisual\":{\"visualType\":\"card\",\"projections\":{\"Values\":[{\"queryRef\":\"Measure Table.Total Female\"}]},\"prototypeQuery\":{\"Version\":2,\"From\":[{\"Name\":\"m\",\"Entity\":\"Measure Table\",\"Type\":0}],\"Select\":[{\"Measure\":{\"Expression\":{\"SourceRef\":{\"Source\":\"m\"}},\"Property\":\"Total Female\"},\"Name\":\"Measure Table.Total Female\",\"NativeReferenceName\":\"Total Female\"}],\"OrderBy\":[{\"Direction\":2,\"Expression\":{\"Measure\":{\"Expression\":{\"SourceRef\":{\"Source\":\"m\"}},\"Property\":\"Total Female\"}}}]},\"drillFilterOtherVisuals\":true,\"hasDefaultSort\":true}}",
          "filters": "[]",
          "height": 101.54,
          "width": 141.34,
          "x": 104.29,
          "y": 359.52,
          "z": 1000.00
        },
        {
          "config": "{\"name\":\"c8cef51ed1e59061985c\",\"layouts\":[{\"id\":0,\"position\":{\"x\":245.62689492286304,\"y\":359.52092999882746,\"z\":2000,\"width\":141.33838087740165,\"height\":101.54407946531768,\"tabOrder\":2000}}],\"singleVisual\":{\"visualType\":\"card\",\"projections\":{\"Values\":[{\"queryRef\":\"Measure Table.Total Male\"}]},\"prototypeQuery\":{\"Version\":2,\"From\":[{\"Name\":\"m\",\"Entity\":\"Measure Table\",\"Type\":0}],\"Select\":[{\"Measure\":{\"Expression\":{\"SourceRef\":{\"Source\":\"m\"}},\"Property\":\"Total Male\"},\"Name\":\"Measure Table.Total Male\",\"NativeReferenceName\":\"Total Male\"}],\"OrderBy\":[{\"Direction\":2,\"Expression\":{\"Measure\":{\"Expression\":{\"SourceRef\":{\"Source\":\"m\"}},\"Property\":\"Total Male\"}}}]},\"drillFilterOtherVisuals\":true,\"hasDefaultSort\":true}}",
          "filters": "[]",
          "height": 101.54,
          "width": 141.34,
          "x": 245.63,
          "y": 359.52,
          "z": 2000.00
        },
        {
          "config": "{\"name\":\"d651e961904fb73c95ad\",\"layouts\":[{\"id\":0,\"position\":{\"x\":32.909038737446195,\"y\":31.341941654710666,\"z\":0,\"width\":424.6833094213295,\"height\":327.5232902917264,\"tabOrder\":0}}],\"singleVisual\":{\"visualType\":\"scatterChart\",\"projections\":{\"Y\":[{\"queryRef\":\"Measure Table.Gender Ratio (F/M)\"}],\"X\":[{\"queryRef\":\"Measure Table.Total Population\",\"active\":true}],\"Category\":[{\"queryRef\":\"US Demographics 2023.state\",\"active\":true}]},\"prototypeQuery\":{\"Version\":2,\"From\":[{\"Name\":\"m\",\"Entity\":\"Measure Table\",\"Type\":0},{\"Name\":\"u\",\"Entity\":\"US Demographics 2023\",\"Type\":0}],\"Select\":[{\"Measure\":{\"Expression\":{\"SourceRef\":{\"Source\":\"m\"}},\"Property\":\"Gender Ratio (F/M)\"},\"Name\":\"Measure Table.Gender Ratio (F/M)\",\"NativeReferenceName\":\"Gender Ratio (F/M)\"},{\"Measure\":{\"Expression\":{\"SourceRef\":{\"Source\":\"m\"}},\"Property\":\"Total Population\"},\"Name\":\"Measure Table.Total Population\",\"NativeReferenceName\":\"Total Population\"},{\"Column\":{\"Expression\":{\"SourceRef\":{\"Source\":\"u\"}},\"Property\":\"state\"},\"Name\":\"US Demographics 2023.state\",\"NativeReferenceName\":\"state\"}]},\"drillFilterOtherVisuals\":true,\"objects\":{\"categoryAxis\":[{\"properties\":{\"logAxisScale\":{\"expr\":{\"Literal\":{\"Value\":\"false\"}}}}}],\"y1AxisReferenceLine\":[{\"properties\":{\"show\":{\"expr\":{\"Literal\":{\"Value\":\"true\"}}},\"displayName\":{\"expr\":{\"Literal\":{\"Value\":\"'Parity'\"}}},\"value\":{\"expr\":{\"Literal\":{\"Value\":\"1D\"}}},\"dataLabelShow\":{\"expr\":{\"Literal\":{\"Value\":\"true\"}}},\"dataLabelHorizontalPosition\":{\"expr\":{\"Literal\":{\"Value\":\"'right'\"}}},\"dataLabelVerticalPosition\":{\"expr\":{\"Literal\":{\"Value\":\"'under'\"}}},\"dataLabelText\":{\"expr\":{\"Literal\":{\"Value\":\"'ValueAndName'\"}}}},\"selector\":{\"id\":\"1\"}}],\"categoryLabels\":[{\"properties\":{\"show\":{\"expr\":{\"Literal\":{\"Value\":\"true\"}}}}}]}}}",
          "filters": "[]",
          "height": 327.52,
          "width": 424.68,
          "x": 32.91,
          "y": 31.34,
          "z": 0.00
        }
      ],
      "width": 1280.00
    },
    {
      "config": "{\"relationships\":[{\"source\":\"c2dbcef0628706924e10\",\"target\":\"d95bf1df513bffc3ca0c\",\"type\":3},{\"source\":\"c2dbcef0628706924e10\",\"target\":\"a3dd02def64d63cdb889\",\"type\":3},{\"source\":\"c2dbcef0628706924e10\",\"target\":\"40df8e4b1544201ec796\",\"type\":3},{\"source\":\"c2dbcef0628706924e10\",\"target\":\"cbec82d405eca04debde\",\"type\":3},{\"source\":\"c2dbcef0628706924e10\",\"target\":\"0c24c7355a073902727b\",\"type\":3},{\"source\":\"c2dbcef0628706924e10\",\"target\":\"464a01c598662970fd7d\",\"type\":3}]}",
      "displayName": "States",
      "displayOption": 1,
      "filters": "[]",
      "height": 720.00,
      "name": "423263650de0dd81d73b",
      "visualContainers": [
        {
          "config": "{\"name\":\"0c24c7355a073902727b\",\"layouts\":[{\"id\":0,\"position\":{\"x\":493.9982244258698,\"y\":495.3704417159417,\"z\":4000,\"width\":246.9991122129349,\"height\":223.67141828171327,\"tabOrder\":4000}}],\"singleVisual\":{\"visualType\":\"multiRowCard\",\"projections\":{\"Values\":[{\"queryRef\":\"Measure Table.Total Population\"},{\"queryRef\":\"Measure Table.Percentage of All US Population\"},{\"queryRef\":\"Measure Table.Number of Counties\"}]},\"prototypeQuery\":{\"Version\":2,\"From\":[{\"Name\":\"m\",\"Entity\":\"Measure Table\",\"Type\":0}],\"Select\":[{\"Measure\":{\"Expression\":{\"SourceRef\":{\"Source\":\"m\"}},\"Property\":\"Total Population\"},\"Name\":\"Measure Table.Total Population\",\"NativeReferenceName\":\"Total Population\"},{\"Measure\":{\"Expression\":{\"SourceRef\":{\"Source\":\"m\"}},\"Property\":\"Percentage of All US Population\"},\"Name\":\"Measure Table.Percentage of All US Population\",\"NativeReferenceName\":\"Percentage of All US Population\"},{\"Measure\":{\"Expression\":{\"SourceRef\":{\"Source\":\"m\"}},\"Property\":\"Number of Counties\"},\"Name\":\"Measure Table.Number of Counties\",\"NativeReferenceName\":\"Number of Counties\"}],\"OrderBy\":[{\"Direction\":2,\"Expression\":{\"Measure\":{\"Expression\":{\"SourceRef\":{\"Source\":\"m\"}},\"Property\":\"Total Population\"}}}]},\"drillFilterOtherVisuals\":true,\"hasDefaultSort\":true,\"objects\":{\"dataLabels\":[{\"properties\":{\"fontSize\":{\"expr\":{\"Literal\":{\"Value\":\"25D\"}}}}}]}}}",
          "filters": "[]",
          "height": 223.67,
          "width": 247.00,
          "x": 494.00,
          "y": 495.37,
          "z": 4000.00
        },
        {
          "config": "{\"name\":\"40df8e4b1544201ec796\",\"layouts\":[{\"id\":0,\"position\":{\"x\":28.207747489239598,\"y\":36.04323290291727,\"z\":5000,\"width\":512.4407460545194,\"height\":354.16394069823053,\"tabOrder\":5000}}],\"singleVisual\":{\"visualType\":\"treemap\",\"projections\":{\"Group\":[{\"queryRef\":\"US Demographics 2023.state Hierarchy.state\",\"active\":true},{\"queryRef\":\"US Demographics 2023.state Hierarchy.county\"}],\"Values\":[{\"queryRef\":\"Measure Table.Total Population\"}]},\"prototypeQuery\":{\"Version\":2,\"From\":[{\"Name\":\"m\",\"Entity\":\"Measure Table\",\"Type\":0},{\"Name\":\"u\",\"Entity\":\"US Demographics 2023\",\"Type\":0}],\"Select\":[{\"HierarchyLevel\":{\"Expression\":{\"Hierarchy\":{\"Expression\":{\"SourceRef\":{\"Source\":\"u\"}},\"Hierarchy\":\"state Hierarchy\"}},\"Level\":\"state\"},\"Name\":\"US Demographics 2023.state Hierarchy.state\",\"NativeReferenceName\":\"state Hierarchy state\"},{\"HierarchyLevel\":{\"Expression\":{\"Hierarchy\":{\"Expression\":{\"SourceRef\":{\"Source\":\"u\"}},\"Hierarchy\":\"state Hierarchy\"}},\"Level\":\"county\"},\"Name\":\"US Demographics 2023.state Hierarchy.county\",\"NativeReferenceName\":\"state Hierarchy county\"},{\"Measure\":{\"Expression\":{\"SourceRef\":{\"Source\":\"m\"}},\"Property\":\"Total Population\"},\"Name\":\"Measure Table.Total Population\",\"NativeReferenceName\":\"Total Population\"}],\"OrderBy\":[{\"Direction\":2,\"Expression\":{\"Measure\":{\"Expression\":{\"SourceRef\":{\"Source\":\"m\"}},\"Property\":\"Total Population\"}}}]},\"drillFilterOtherVisuals\":true,\"hasDefaultSort\":true}}",
          "filters": "[]",
          "height": 354.16,
          "width": 512.44,
          "x": 28.21,
          "y": 36.04,
          "z": 5000.00
        },
        {
          "config": "{\"name\":\"464a01c598662970fd7d\",\"layouts\":[{\"id\":0,\"position\":{\"x\":28.207747489239598,\"y\":390.20717360114776,\"z\":0,\"width\":465.4278335724534,\"height\":329.09038737446195,\"tabOrder\":0}}],\"singleVisual\":{\"visualType\":\"clusteredBarChart\",\"projections\":{\"Y\":[{\"queryRef\":\"Measure Table.Total Population\"}],\"Category\":[{\"queryRef\":\"US Demographics 2023.state\",\"active\":true}]},\"prototypeQuery\":{\"Version\":2,\"From\":[{\"Name\":\"m\",\"Entity\":\"Measure Table\",\"Type\":0},{\"Name\":\"u\",\"Entity\":\"US Demographics 2023\",\"Type\":0}],\"Select\":[{\"Measure\":{\"Expression\":{\"SourceRef\":{\"Source\":\"m\"}},\"Property\":\"Total Population\"},\"Name\":\"Measure Table.Total Population\",\"NativeReferenceName\":\"Total Population\"},{\"Column\":{\"Expression\":{\"SourceRef\":{\"Source\":\"u\"}},\"Property\":\"state\"},\"Name\":\"US Demographics 2023.state\",\"NativeReferenceName\":\"state\"}],\"OrderBy\":[{\"Direction\":2,\"Expression\":{\"Measure\":{\"Expression\":{\"SourceRef\":{\"Source\":\"m\"}},\"Property\":\"Total Population\"}}}]},\"drillFilterOtherVisuals\":true,\"objects\":{\"labels\":[{\"properties\":{\"show\":{\"expr\":{\"Literal\":{\"Value\":\"true\"}}}}}]}}}",
          "filters": "[]",
          "height": 329.09,
          "width": 465.43,
          "x": 28.21,
          "y": 390.21,
          "z": 0.00
        },
        {
          "config": "{\"name\":\"58bcd1c5c00d25fdba4e\",\"layouts\":[{\"id\":0,\"position\":{\"x\":493.9982244258698,\"y\":389.7097103804084,\"z\":1000,\"width\":246.9991122129349,\"height\":105.66073133553327,\"tabOrder\":1000}}],\"singleVisual\":{\"visualType\":\"card\",\"projections\":{\"Values\":[{\"queryRef\":\"Measure Table.All US Population\"}]},\"prototypeQuery\":{\"Version\":2,\"From\":[{\"Name\":\"m\",\"Entity\":\"Measure Table\",\"Type\":0}],\"Select\":[{\"Measure\":{\"Expression\":{\"SourceRef\":{\"Source\":\"m\"}},\"Property\":\"All US Population\"},\"Name\":\"Measure Table.All US Population\",\"NativeReferenceName\":\"All US Population\"}],\"OrderBy\":[{\"Direction\":2,\"Expression\":{\"Measure\":{\"Expression\":{\"SourceRef\":{\"Source\":\"m\"}},\"Property\":\"All US Population\"}}}]},\"drillFilterOtherVisuals\":true,\"hasDefaultSort\":true}}",
          "filters": "[]",
          "height": 105.66,
          "width": 247.00,
          "x": 494.00,
          "y": 389.71,
          "z": 1000.00
        },
        {
          "config": "{\"name\":\"a3dd02def64d63cdb889\",\"layouts\":[{\"id\":0,\"position\":{\"x\":562.6090889294628,\"y\":46.65538786244326,\"z\":2000,\"width\":389.7097103804084,\"height\":343.05432251796515,\"tabOrder\":2000}}],\"singleVisual\":{\"visualType\":\"scatterChart\",\"projections\":{\"X\":[{\"queryRef\":\"Measure Table.Total Population\",\"active\":true}],\"Y\":[{\"queryRef\":\"Measure Table.Number of Counties\"}],\"Category\":[{\"queryRef\":\"US Demographics 2023.state\",\"active\":true}]},\"prototypeQuery\":{\"Version\":2,\"From\":[{\"Name\":\"m\",\"Entity\":\"Measure Table\",\"Type\":0},{\"Name\":\"u\",\"Entity\":\"US Demographics 2023\",\"Type\":0}],\"Select\":[{\"Measure\":{\"Expression\":{\"SourceRef\":{\"Source\":\"m\"}},\"Property\":\"Total Population\"},\"Name\":\"Measure Table.Total Population\",\"NativeReferenceName\":\"Total Population\"},{\"Measure\":{\"Expression\":{\"SourceRef\":{\"Source\":\"m\"}},\"Property\":\"Number of Counties\"},\"Name\":\"Measure Table.Number of Counties\",\"NativeReferenceName\":\"Number of Counties\"},{\"Column\":{\"Expression\":{\"SourceRef\":{\"Source\":\"u\"}},\"Property\":\"state\"},\"Name\":\"US Demographics 2023.state\",\"NativeReferenceName\":\"state\"}]},\"drillFilterOtherVisuals\":true,\"objects\":{\"trend\":[{\"properties\":{\"show\":{\"expr\":{\"Literal\":{\"Value\":\"true\"}}},\"displayName\":{\"expr\":{\"Literal\":{\"Value\":\"'Trend line 1'\"}}}}}],\"categoryLabels\":[{\"properties\":{\"show\":{\"expr\":{\"Literal\":{\"Value\":\"true\"}}}}}]}}}",
          "filters": "[]",
          "height": 343.05,
          "width": 389.71,
          "x": 562.61,
          "y": 46.66,
          "z": 2000.00
        },
        {
          "config": "{\"name\":\"c2dbcef0628706924e10\",\"layouts\":[{\"id\":0,\"position\":{\"x\":983.879796981524,\"y\":316.9821940065998,\"z\":7000,\"width\":285.421196334947,\"height\":126.24399068661117,\"tabOrder\":7000}}],\"singleVisual\":{\"visualType\":\"multiRowCard\",\"projections\":{\"Values\":[{\"queryRef\":\"Measure Table.Number of Counties\"},{\"queryRef\":\"US Demographics 2023.state\"}]},\"prototypeQuery\":{\"Version\":2,\"From\":[{\"Name\":\"m\",\"Entity\":\"Measure Table\",\"Type\":0},{\"Name\":\"u\",\"Entity\":\"US Demographics 2023\",\"Type\":0}],\"Select\":[{\"Measure\":{\"Expression\":{\"SourceRef\":{\"Source\":\"m\"}},\"Property\":\"Number of Counties\"},\"Name\":\"Measure Table.Number of Counties\",\"NativeReferenceName\":\"Number of Counties\"},{\"Column\":{\"Expression\":{\"SourceRef\":{\"Source\":\"u\"}},\"Property\":\"state\"},\"Name\":\"US Demographics 2023.state\",\"NativeReferenceName\":\"state\"}],\"OrderBy\":[{\"Direction\":2,\"Expression\":{\"Measure\":{\"Expression\":{\"SourceRef\":{\"Source\":\"m\"}},\"Property\":\"Number of Counties\"}}}]},\"drillFilterOtherVisuals\":true,\"hasDefaultSort\":true,\"objects\":{\"dataLabels\":[{\"properties\":{\"fontSize\":{\"expr\":{\"Literal\":{\"Value\":\"25D\"}}}}}]},\"vcObjects\":{\"title\":[{\"properties\":{\"show\":{\"expr\":{\"Literal\":{\"Value\":\"true\"}}},\"text\":{\"expr\":{\"Literal\":{\"Value\":\"'Most Populated State'\"}}}}}]}}}",
          "filters": "[{\"name\":\"5e2b9cf033b51a83890b\",\"expression\":{\"Column\":{\"Expression\":{\"SourceRef\":{\"Entity\":\"US Demographics 2023\"}},\"Property\":\"state\"}},\"filter\":{\"Version\":2,\"From\":[{\"Name\":\"subquery\",\"Expression\":{\"Subquery\":{\"Query\":{\"Version\":2,\"From\":[{\"Name\":\"u\",\"Entity\":\"US Demographics 2023\",\"Type\":0},{\"Name\":\"m\",\"Entity\":\"Measure Table\",\"Type\":0}],\"Select\":[{\"Column\":{\"Expression\":{\"SourceRef\":{\"Source\":\"u\"}},\"Property\":\"state\"},\"Name\":\"field\"}],\"OrderBy\":[{\"Direction\":2,\"Expression\":{\"Measure\":{\"Expression\":{\"SourceRef\":{\"Source\":\"m\"}},\"Property\":\"Total Population\"}}}],\"Top\":1}}},\"Type\":2},{\"Name\":\"u\",\"Entity\":\"US Demographics 2023\",\"Type\":0}],\"Where\":[{\"Condition\":{\"In\":{\"Expressions\":[{\"Column\":{\"Expression\":{\"SourceRef\":{\"Source\":\"u\"}},\"Property\":\"state\"}}],\"Table\":{\"SourceRef\":{\"Source\":\"subquery\"}}}}}]},\"type\":\"TopN\",\"howCreated\":0}]",
          "height": 126.24,
          "width": 285.42,
          "x": 983.88,
          "y": 316.98,
          "z": 7000.00
        },
        {
          "config": "{\"name\":\"cbec82d405eca04debde\",\"layouts\":[{\"id\":0,\"position\":{\"x\":757.4639441196671,\"y\":466.55387862443257,\"z\":6000,\"width\":473.4149650747919,\"height\":253.8601986632942,\"tabOrder\":6000}}],\"singleVisual\":{\"visualType\":\"lineClusteredColumnComboChart\",\"projections\":{\"Category\":[{\"queryRef\":\"US Demographics 2023.state\",\"active\":true}],\"Y\":[{\"queryRef\":\"Measure Table.Number of Counties\"}],\"Y2\":[{\"queryRef\":\"Measure Table.Total Population\"}]},\"prototypeQuery\":{\"Version\":2,\"From\":[{\"Name\":\"m\",\"Entity\":\"Measure Table\",\"Type\":0},{\"Name\":\"u\",\"Entity\":\"US Demographics 2023\",\"Type\":0}],\"Select\":[{\"Column\":{\"Expression\":{\"SourceRef\":{\"Source\":\"u\"}},\"Property\":\"state\"},\"Name\":\"US Demographics 2023.state\",\"NativeReferenceName\":\"state\"},{\"Measure\":{\"Expression\":{\"SourceRef\":{\"Source\":\"m\"}},\"Property\":\"Number of Counties\"},\"Name\":\"Measure Table.Number of Counties\",\"NativeReferenceName\":\"Number of Counties\"},{\"Measure\":{\"Expression\":{\"SourceRef\":{\"Source\":\"m\"}},\"Property\":\"Total Population\"},\"Name\":\"Measure Table.Total Population\",\"NativeReferenceName\":\"Total Population\"}],\"OrderBy\":[{\"Direction\":1,\"Expression\":{\"Measure\":{\"Expression\":{\"SourceRef\":{\"Source\":\"m\"}},\"Property\":\"Total Population\"}}}]},\"columnProperties\":{\"Measure Table.Percentage of All US Population\":{\"formatString\":null}},\"drillFilterOtherVisuals\":true,\"objects\":{\"legend\":[{\"properties\":{\"show\":{\"expr\":{\"Literal\":{\"Value\":\"true\"}}}}}],\"labels\":[{\"properties\":{\"show\":{\"expr\":{\"Literal\":{\"Value\":\"true\"}}}}},{\"properties\":{\"showSeries\":{\"expr\":{\"Literal\":{\"Value\":\"false\"}}}},\"selector\":{\"metadata\":\"Measure Table.Total Population\"}},{\"properties\":{\"labelPosition\":{\"expr\":{\"Literal\":{\"Value\":\"'OutsideEnd'\"}}}},\"selector\":{\"metadata\":\"Measure Table.Number of Counties\"}}],\"valueAxis\":[{\"properties\":{\"alignZeros\":{\"expr\":{\"Literal\":{\"Value\":\"true\"}}}}}],\"dataPoint\":[{\"properties\":{\"fill\":{\"solid\":{\"color\":{\"expr\":{\"ThemeDataColor\":{\"ColorId\":2,\"Percent\":0}}}}}},\"selector\":{\"metadata\":\"Measure Table.Total Population\"}},{\"properties\":{\"fill\":{\"solid\":{\"color\":{\"expr\":{\"ThemeDataColor\":{\"ColorId\":3,\"Percent\":0}}}}}}}]},\"vcObjects\":{\"title\":[{\"properties\":{\"show\":{\"expr\":{\"Literal\":{\"Value\":\"true\"}}},\"text\":{\"expr\":{\"Literal\":{\"Value\":\"'# of Counties and Population of 10 Least Populated States'\"}}},\"fontSize\":{\"expr\":{\"Literal\":{\"Value\":\"20D\"}}}}}]}}}",
          "filters": "[{\"expression\":{\"Column\":{\"Expression\":{\"SourceRef\":{\"Entity\":\"US Demographics 2023\"}},\"Property\":\"state\"}},\"filter\":{\"Version\":2,\"From\":[{\"Name\":\"subquery\",\"Expression\":{\"Subquery\":{\"Query\":{\"Version\":2,\"From\":[{\"Name\":\"u\",\"Entity\":\"US Demographics 2023\",\"Type\":0},{\"Name\":\"m\",\"Entity\":\"Measure Table\",\"Type\":0}],\"Select\":[{\"Column\":{\"Expression\":{\"SourceRef\":{\"Source\":\"u\"}},\"Property\":\"state\"},\"Name\":\"field\"}],\"OrderBy\":[{\"Direction\":1,\"Expression\":{\"Measure\":{\"Expression\":{\"SourceRef\":{\"Source\":\"m\"}},\"Property\":\"Total Population\"}}}],\"Top\":10}}},\"Type\":2},{\"Name\":\"u\",\"Entity\":\"US Demographics 2023\",\"Type\":0}],\"Where\":[{\"Condition\":{\"In\":{\"Expressions\":[{\"Column\":{\"Expression\":{\"SourceRef\":{\"Source\":\"u\"}},\"Property\":\"state\"}}],\"Table\":{\"SourceRef\":{\"Source\":\"subquery\"}}}}}]},\"type\":\"TopN\",\"howCreated\":0,\"isHiddenInViewMode\":false}]",
          "height": 253.86,
          "width": 473.41,
          "x": 757.46,
          "y": 466.55,
          "z": 6000.00
        },
        {
          "config": "{\"name\":\"d95bf1df513bffc3ca0c\",\"layouts\":[{\"id\":0,\"position\":{\"x\":971.5298413708773,\"y\":46.65538786244326,\"z\":3000,\"width\":308.74889026616864,\"height\":227.78807015192885,\"tabOrder\":3000}}],\"singleVisual\":{\"visualType\":\"filledMap\",\"projections\":{\"Category\":[{\"queryRef\":\"public us_demographics_data_2023.state\",\"active\":true}]},\"prototypeQuery\":{\"Version\":2,\"From\":[{\"Name\":\"p\",\"Entity\":\"US Demographics 2023\",\"Type\":0}],\"Select\":[{\"Column\":{\"Expression\":{\"SourceRef\":{\"Source\":\"p\"}},\"Property\":\"state\"},\"Name\":\"public us_demographics_data_2023.state\",\"NativeReferenceName\":\"state\"}]},\"drillFilterOtherVisuals\":true,\"objects\":{\"dataPoint\":[{\"properties\":{\"fill\":{\"solid\":{\"color\":{\"expr\":{\"FillRule\":{\"Input\":{\"Measure\":{\"Expression\":{\"SourceRef\":{\"Entity\":\"Measure Table\"}},\"Property\":\"Total Population\"}},\"FillRule\":{\"linearGradient2\":{\"min\":{\"color\":{\"Literal\":{\"Value\":\"'#FFFFFF'\"}}},\"max\":{\"color\":{\"Literal\":{\"Value\":\"'#FF0000'\"}}},\"nullColoringStrategy\":{\"strategy\":{\"Literal\":{\"Value\":\"'asZero'\"}}}}}}}}}}},\"selector\":{\"data\":[{\"dataViewWildcard\":{\"matchingOption\":1}}]}},{\"properties\":{\"fillRule\":{\"linearGradient2\":{\"min\":{\"color\":{\"expr\":{\"Literal\":{\"Value\":\"'minColor'\"}}}},\"max\":{\"color\":{\"expr\":{\"Literal\":{\"Value\":\"'maxColor'\"}}}},\"nullColoringStrategy\":{\"strategy\":{\"expr\":{\"Literal\":{\"Value\":\"'asZero'\"}}}}}}}}],\"mapControls\":[{\"properties\":{\"autoZoom\":{\"expr\":{\"Literal\":{\"Value\":\"false\"}}},\"showZoomButtons\":{\"expr\":{\"Literal\":{\"Value\":\"true\"}}},\"centerLatitude\":{\"expr\":{\"Literal\":{\"Value\":\"40.71410037704322D\"}}},\"centerLongitude\":{\"expr\":{\"Literal\":{\"Value\":\"-98.89298195480721D\"}}},\"zoomLevel\":{\"expr\":{\"Literal\":{\"Value\":\"3D\"}}},\"showLassoButton\":{\"expr\":{\"Literal\":{\"Value\":\"false\"}}}}}],\"mapStyles\":[{\"properties\":{\"mapTheme\":{\"expr\":{\"Literal\":{\"Value\":\"'canvasLight'\"}}}}}]}}}",
          "filters": "[]",
          "height": 227.79,
          "width": 308.75,
          "x": 971.53,
          "y": 46.66,
          "z": 3000.00
        }
      ],
      "width": 1280.00
    },
    {
      "config": "{}",
      "displayName": "Race",
      "displayOption": 1,
      "filters": "[]",
      "height": 720.00,
      "name": "7938c3abf53fe07f5a3e",
      "ordinal": 1,
      "visualContainers": [
        {
          "config": "{\"name\":\"000b8ea93c76084d8b8e\",\"layouts\":[{\"id\":0,\"position\":{\"x\":21.939359158297464,\"y\":45.44581539933046,\"z\":4000,\"width\":396.47556193208993,\"height\":360.43232902917265,\"tabOrder\":4000}}],\"singleVisual\":{\"visualType\":\"barChart\",\"projections\":{\"Category\":[{\"queryRef\":\"US Demographics 2023.state Hierarchy.state\",\"active\":true},{\"queryRef\":\"US Demographics 2023.state Hierarchy.county\"}],\"Y\":[{\"queryRef\":\"Measure Table.Total White\"},{\"queryRef\":\"Measure Table.Total Black\"},{\"queryRef\":\"Measure Table.Total Other Race\"}]},\"prototypeQuery\":{\"Version\":2,\"From\":[{\"Name\":\"u\",\"Entity\":\"US Demographics 2023\",\"Type\":0},{\"Name\":\"m\",\"Entity\":\"Measure Table\",\"Type\":0}],\"Select\":[{\"HierarchyLevel\":{\"Expression\":{\"Hierarchy\":{\"Expression\":{\"SourceRef\":{\"Source\":\"u\"}},\"Hierarchy\":\"state Hierarchy\"}},\"Level\":\"state\"},\"Name\":\"US Demographics 2023.state Hierarchy.state\",\"NativeReferenceName\":\"state Hierarchy state\"},{\"HierarchyLevel\":{\"Expression\":{\"Hierarchy\":{\"Expression\":{\"SourceRef\":{\"Source\":\"u\"}},\"Hierarchy\":\"state Hierarchy\"}},\"Level\":\"county\"},\"Name\":\"US Demographics 2023.state Hierarchy.county\",\"NativeReferenceName\":\"state Hierarchy county\"},{\"Measure\":{\"Expression\":{\"SourceRef\":{\"Source\":\"m\"}},\"Property\":\"Total Black\"},\"Name\":\"Measure Table.Total Black\",\"NativeReferenceName\":\"Total Black\"},{\"Measure\":{\"Expression\":{\"SourceRef\":{\"Source\":\"m\"}},\"Property\":\"Total White\"},\"Name\":\"Measure Table.Total White\",\"NativeReferenceName\":\"Total White\"},{\"Measure\":{\"Expression\":{\"SourceRef\":{\"Source\":\"m\"}},\"Property\":\"Total Other Race\"},\"Name\":\"Measure Table.Total Other Race\",\"NativeReferenceName\":\"Total Other Race\"}],\"OrderBy\":[{\"Direction\":2,\"Expression\":{\"Measure\":{\"Expression\":{\"SourceRef\":{\"Source\":\"m\"}},\"Property\":\"Total White\"}}}]},\"drillFilterOtherVisuals\":true,\"hasDefaultSort\":true,\"objects\":{\"dataPoint\":[{\"properties\":{\"fill\":{\"solid\":{\"color\":{\"expr\":{\"ThemeDataColor\":{\"ColorId\":1,\"Percent\":0.4}}}}}},\"selector\":{\"metadata\":\"Measure Table.Total Black\"}},{\"properties\":{\"fill\":{\"solid\":{\"color\":{\"expr\":{\"ThemeDataColor\":{\"ColorId\":2,\"Percent\":0}}}}}},\"selector\":{\"metadata\":\"Measure Table.Total White\"}},{\"properties\":{\"fill\":{\"solid\":{\"color\":{\"expr\":{\"ThemeDataColor\":{\"ColorId\":8,\"Percent\":0}}}}}},\"selector\":{\"metadata\":\"Measure Table.Total Other Race\"}}]}}}",
          "filters": "[]",
          "height": 360.43,
          "width": 396.48,
          "x": 21.94,
          "y": 45.45,
          "z": 4000.00
        },
        {
          "config": "{\"name\":\"17eec87620d69812a069\",\"layouts\":[{\"id\":0,\"position\":{\"x\":646.3143436238463,\"y\":551.6313506088879,\"z\":3000,\"width\":256.60463324343795,\"height\":149.5716846178328,\"tabOrder\":3000}}],\"singleVisual\":{\"visualType\":\"card\",\"projections\":{\"Values\":[{\"queryRef\":\"Measure Table.Percentage of Hispanics\"}]},\"prototypeQuery\":{\"Version\":2,\"From\":[{\"Name\":\"m\",\"Entity\":\"Measure Table\",\"Type\":0}],\"Select\":[{\"Measure\":{\"Expression\":{\"SourceRef\":{\"Source\":\"m\"}},\"Property\":\"Percentage Hispanics\"},\"Name\":\"Measure Table.Percentage of Hispanics\",\"NativeReferenceName\":\"Percentage Hispanics\"}],\"OrderBy\":[{\"Direction\":2,\"Expression\":{\"Measure\":{\"Expression\":{\"SourceRef\":{\"Source\":\"m\"}},\"Property\":\"Percentage Hispanics\"}}}]},\"drillFilterOtherVisuals\":true,\"hasDefaultSort\":true}}",
          "filters": "[]",
          "height": 149.57,
          "width": 256.60,
          "x": 646.31,
          "y": 551.63,
          "z": 3000.00
        },
        {
          "config": "{\"name\":\"26e006db540f91d90d7f\",\"layouts\":[{\"id\":0,\"position\":{\"x\":23.32769393122163,\"y\":406.1763178612707,\"z\":0,\"width\":616.1255632422655,\"height\":290.91006549523445,\"tabOrder\":0}}],\"singleVisual\":{\"visualType\":\"pivotTable\",\"projections\":{\"Rows\":[{\"queryRef\":\"public us_demographics_data_2023.state Hierarchy.state\",\"active\":true},{\"queryRef\":\"public us_demographics_data_2023.state Hierarchy.county\"}],\"Values\":[{\"queryRef\":\"Measure Table.Total African American\"},{\"queryRef\":\"Measure Table.Percentage of African America\"},{\"queryRef\":\"Measure Table.Total Hispanics or Latino\"},{\"queryRef\":\"Measure Table.Percentage of Hispanics or Latino\"}]},\"prototypeQuery\":{\"Version\":2,\"From\":[{\"Name\":\"p\",\"Entity\":\"US Demographics 2023\",\"Type\":0},{\"Name\":\"m\",\"Entity\":\"Measure Table\",\"Type\":0}],\"Select\":[{\"HierarchyLevel\":{\"Expression\":{\"Hierarchy\":{\"Expression\":{\"SourceRef\":{\"Source\":\"p\"}},\"Hierarchy\":\"state Hierarchy\"}},\"Level\":\"state\"},\"Name\":\"public us_demographics_data_2023.state Hierarchy.state\",\"NativeReferenceName\":\"state Hierarchy state\"},{\"HierarchyLevel\":{\"Expression\":{\"Hierarchy\":{\"Expression\":{\"SourceRef\":{\"Source\":\"p\"}},\"Hierarchy\":\"state Hierarchy\"}},\"Level\":\"county\"},\"Name\":\"public us_demographics_data_2023.state Hierarchy.county\",\"NativeReferenceName\":\"state Hierarchy county\"},{\"Measure\":{\"Expression\":{\"SourceRef\":{\"Source\":\"m\"}},\"Property\":\"Total Black\"},\"Name\":\"Measure Table.Total African American\",\"NativeReferenceName\":\"Total Black\"},{\"Measure\":{\"Expression\":{\"SourceRef\":{\"Source\":\"m\"}},\"Property\":\"Total Hispanics\"},\"Name\":\"Measure Table.Total Hispanics or Latino\",\"NativeReferenceName\":\"Total Hispanics\"},{\"Measure\":{\"Expression\":{\"SourceRef\":{\"Source\":\"m\"}},\"Property\":\"Percentage Black\"},\"Name\":\"Measure Table.Percentage of African America\",\"NativeReferenceName\":\"Percentage Black\"},{\"Measure\":{\"Expression\":{\"SourceRef\":{\"Source\":\"m\"}},\"Property\":\"Percentage Hispanics\"},\"Name\":\"Measure Table.Percentage of Hispanics or Latino\",\"NativeReferenceName\":\"Percentage Hispanics\"}],\"OrderBy\":[{\"Direction\":2,\"Expression\":{\"Measure\":{\"Expression\":{\"SourceRef\":{\"Source\":\"m\"}},\"Property\":\"Total Black\"}}}]},\"drillFilterOtherVisuals\":true}}",
          "filters": "[]",
          "height": 290.91,
          "width": 616.13,
          "x": 23.33,
          "y": 406.18,
          "z": 0.00
        },
        {
          "config": "{\"name\":\"35e52f944381db05d4db\",\"layouts\":[{\"id\":0,\"position\":{\"x\":792.9511238641799,\"y\":45.44581539933046,\"z\":1000,\"width\":454.4581539933046,\"height\":360.43232902917265,\"tabOrder\":1000}}],\"singleVisual\":{\"visualType\":\"scatterChart\",\"projections\":{\"Category\":[{\"queryRef\":\"US Demographics 2023.state\",\"active\":true}],\"X\":[{\"queryRef\":\"Measure Table.Total Population\",\"active\":true}],\"Y\":[{\"queryRef\":\"Measure Table.Percentage Race\"}],\"Series\":[{\"queryRef\":\"Race.race\"}]},\"prototypeQuery\":{\"Version\":2,\"From\":[{\"Name\":\"u\",\"Entity\":\"US Demographics 2023\",\"Type\":0},{\"Name\":\"m\",\"Entity\":\"Measure Table\",\"Type\":0},{\"Name\":\"r\",\"Entity\":\"Race\",\"Type\":0}],\"Select\":[{\"Column\":{\"Expression\":{\"SourceRef\":{\"Source\":\"u\"}},\"Property\":\"state\"},\"Name\":\"US Demographics 2023.state\",\"NativeReferenceName\":\"state\"},{\"Measure\":{\"Expression\":{\"SourceRef\":{\"Source\":\"m\"}},\"Property\":\"Total Population\"},\"Name\":\"Measure Table.Total Population\",\"NativeReferenceName\":\"Total Population\"},{\"Measure\":{\"Expression\":{\"SourceRef\":{\"Source\":\"m\"}},\"Property\":\"Percentage Race\"},\"Name\":\"Measure Table.Percentage Race\",\"NativeReferenceName\":\"Percentage Race\"},{\"Column\":{\"Expression\":{\"SourceRef\":{\"Source\":\"r\"}},\"Property\":\"race\"},\"Name\":\"Race.race\",\"NativeReferenceName\":\"race\"}]},\"drillFilterOtherVisuals\":true,\"objects\":{\"categoryAxis\":[{\"properties\":{\"logAxisScale\":{\"expr\":{\"Literal\":{\"Value\":\"true\"}}}}}],\"dataPoint\":[{\"properties\":{\"fill\":{\"solid\":{\"color\":{\"expr\":{\"ThemeDataColor\":{\"ColorId\":1,\"Percent\":0.4}}}}}},\"selector\":{\"data\":[{\"scopeId\":{\"Comparison\":{\"ComparisonKind\":0,\"Left\":{\"Column\":{\"Expression\":{\"SourceRef\":{\"Entity\":\"Race\"}},\"Property\":\"race\"}},\"Right\":{\"Literal\":{\"Value\":\"'Black'\"}}}}}]}},{\"properties\":{\"fill\":{\"solid\":{\"color\":{\"expr\":{\"ThemeDataColor\":{\"ColorId\":4,\"Percent\":0}}}}}},\"selector\":{\"data\":[{\"scopeId\":{\"Comparison\":{\"ComparisonKind\":0,\"Left\":{\"Column\":{\"Expression\":{\"SourceRef\":{\"Entity\":\"Race\"}},\"Property\":\"race\"}},\"Right\":{\"Literal\":{\"Value\":\"'Hispanics'\"}}}}}]}}],\"markers\":[{\"properties\":{\"transparency\":{\"expr\":{\"Literal\":{\"Value\":\"30D\"}}}},\"selector\":{\"data\":[{\"scopeId\":{\"Comparison\":{\"ComparisonKind\":0,\"Left\":{\"Column\":{\"Expression\":{\"SourceRef\":{\"Entity\":\"Race\"}},\"Property\":\"race\"}},\"Right\":{\"Literal\":{\"Value\":\"'Hispanics'\"}}}}}]}},{\"properties\":{\"transparency\":{\"expr\":{\"Literal\":{\"Value\":\"30D\"}}}},\"selector\":{\"data\":[{\"scopeId\":{\"Comparison\":{\"ComparisonKind\":0,\"Left\":{\"Column\":{\"Expression\":{\"SourceRef\":{\"Entity\":\"Race\"}},\"Property\":\"race\"}},\"Right\":{\"Literal\":{\"Value\":\"'Black'\"}}}}}]}}],\"categoryLabels\":[{\"properties\":{\"show\":{\"expr\":{\"Literal\":{\"Value\":\"false\"}}},\"enableBackground\":{\"expr\":{\"Literal\":{\"Value\":\"false\"}}}}}],\"trend\":[{\"properties\":{\"show\":{\"expr\":{\"Literal\":{\"Value\":\"true\"}}},\"displayName\":{\"expr\":{\"Literal\":{\"Value\":\"'Trend line 1'\"}}}}}]}}}",
          "filters": "[{\"name\":\"e984cbf3b0d7e81101b9\",\"expression\":{\"Column\":{\"Expression\":{\"SourceRef\":{\"Entity\":\"Race\"}},\"Property\":\"race\"}},\"filter\":{\"Version\":2,\"From\":[{\"Name\":\"r\",\"Entity\":\"Race\",\"Type\":0}],\"Where\":[{\"Condition\":{\"In\":{\"Expressions\":[{\"Column\":{\"Expression\":{\"SourceRef\":{\"Source\":\"r\"}},\"Property\":\"race\"}}],\"Values\":[[{\"Literal\":{\"Value\":\"'Black'\"}}],[{\"Literal\":{\"Value\":\"'Hispanics'\"}}]]}}}]},\"type\":\"Categorical\",\"howCreated\":0,\"objects\":{},\"isHiddenInViewMode\":false}]",
          "height": 360.43,
          "width": 454.46,
          "x": 792.95,
          "y": 45.45,
          "z": 1000.00
        },
        {
          "config": "{\"name\":\"88c710526b0a6d6a7aa1\",\"layouts\":[{\"id\":0,\"position\":{\"x\":418.4149210903874,\"y\":45.44581539933046,\"z\":5000,\"width\":374.53620277379247,\"height\":360.43232902917265,\"tabOrder\":5000}}],\"singleVisual\":{\"visualType\":\"barChart\",\"projections\":{\"Category\":[{\"queryRef\":\"US Demographics 2023.state Hierarchy.state\",\"active\":true},{\"queryRef\":\"US Demographics 2023.state Hierarchy.county\"}],\"Y\":[{\"queryRef\":\"Measure Table.Total Hispanics\"},{\"queryRef\":\"Measure Table.Total Non Hispanics\"}]},\"prototypeQuery\":{\"Version\":2,\"From\":[{\"Name\":\"u\",\"Entity\":\"US Demographics 2023\",\"Type\":0},{\"Name\":\"m\",\"Entity\":\"Measure Table\",\"Type\":0}],\"Select\":[{\"HierarchyLevel\":{\"Expression\":{\"Hierarchy\":{\"Expression\":{\"SourceRef\":{\"Source\":\"u\"}},\"Hierarchy\":\"state Hierarchy\"}},\"Level\":\"state\"},\"Name\":\"US Demographics 2023.state Hierarchy.state\",\"NativeReferenceName\":\"state Hierarchy state\"},{\"HierarchyLevel\":{\"Expression\":{\"Hierarchy\":{\"Expression\":{\"SourceRef\":{\"Source\":\"u\"}},\"Hierarchy\":\"state Hierarchy\"}},\"Level\":\"county\"},\"Name\":\"US Demographics 2023.state Hierarchy.county\",\"NativeReferenceName\":\"state Hierarchy county\"},{\"Measure\":{\"Expression\":{\"SourceRef\":{\"Source\":\"m\"}},\"Property\":\"Total Non Hispanics\"},\"Name\":\"Measure Table.Total Non Hispanics\",\"NativeReferenceName\":\"Total Non Hispanics\"},{\"Measure\":{\"Expression\":{\"SourceRef\":{\"Source\":\"m\"}},\"Property\":\"Total Hispanics\"},\"Name\":\"Measure Table.Total Hispanics\",\"NativeReferenceName\":\"Total Hispanics\"}],\"OrderBy\":[{\"Direction\":2,\"Expression\":{\"Measure\":{\"Expression\":{\"SourceRef\":{\"Source\":\"m\"}},\"Property\":\"Total Hispanics\"}}}]},\"drillFilterOtherVisuals\":true,\"hasDefaultSort\":true,\"objects\":{\"dataPoint\":[{\"properties\":{\"fill\":{\"solid\":{\"color\":{\"expr\":{\"ThemeDataColor\":{\"ColorId\":4,\"Percent\":0}}}}}},\"selector\":{\"metadata\":\"Measure Table.Total Hispanics\"}},{\"properties\":{\"fill\":{\"solid\":{\"color\":{\"expr\":{\"ThemeDataColor\":{\"ColorId\":2,\"Percent\":0}}}}}},\"selector\":{\"metadata\":\"Measure Table.Total Non Hispanics\"}}]}}}",
          "filters": "[]",
          "height": 360.43,
          "width": 374.54,
          "x": 418.41,
          "y": 45.45,
          "z": 5000.00
        },
        {
          "config": "{\"name\":\"90222f563ec6e9380404\",\"layouts\":[{\"id\":0,\"position\":{\"x\":646.3143436238463,\"y\":406.1763178612707,\"z\":2000,\"width\":256.60463324343795,\"height\":159.1772056483358,\"tabOrder\":2000}}],\"singleVisual\":{\"visualType\":\"card\",\"projections\":{\"Values\":[{\"queryRef\":\"Measure Table.Percentage of Black\"}]},\"prototypeQuery\":{\"Version\":2,\"From\":[{\"Name\":\"m\",\"Entity\":\"Measure Table\",\"Type\":0}],\"Select\":[{\"Measure\":{\"Expression\":{\"SourceRef\":{\"Source\":\"m\"}},\"Property\":\"Percentage Black\"},\"Name\":\"Measure Table.Percentage of Black\",\"NativeReferenceName\":\"Percentage Black\"}],\"OrderBy\":[{\"Direction\":2,\"Expression\":{\"Measure\":{\"Expression\":{\"SourceRef\":{\"Source\":\"m\"}},\"Property\":\"Percentage Black\"}}}]},\"drillFilterOtherVisuals\":true,\"hasDefaultSort\":true}}",
          "filters": "[]",
          "height": 159.18,
          "width": 256.60,
          "x": 646.31,
          "y": 406.18,
          "z": 2000.00
        },
        {
          "config": "{\"name\":\"af5b3161e7c09100c7b1\",\"layouts\":[{\"id\":0,\"position\":{\"x\":929.2885700621712,\"y\":405.8781444285031,\"z\":6000,\"width\":351.0297465327594,\"height\":296.1813486370158,\"tabOrder\":6000}}],\"singleVisual\":{\"visualType\":\"pieChart\",\"projections\":{\"Y\":[{\"queryRef\":\"Measure Table.Total Black\"},{\"queryRef\":\"Measure Table.Total White\"},{\"queryRef\":\"Measure Table.Total Other Race\"}]},\"prototypeQuery\":{\"Version\":2,\"From\":[{\"Name\":\"m\",\"Entity\":\"Measure Table\",\"Type\":0}],\"Select\":[{\"Measure\":{\"Expression\":{\"SourceRef\":{\"Source\":\"m\"}},\"Property\":\"Total Black\"},\"Name\":\"Measure Table.Total Black\",\"NativeReferenceName\":\"Total Black\"},{\"Measure\":{\"Expression\":{\"SourceRef\":{\"Source\":\"m\"}},\"Property\":\"Total White\"},\"Name\":\"Measure Table.Total White\",\"NativeReferenceName\":\"Total White\"},{\"Measure\":{\"Expression\":{\"SourceRef\":{\"Source\":\"m\"}},\"Property\":\"Total Other Race\"},\"Name\":\"Measure Table.Total Other Race\",\"NativeReferenceName\":\"Total Other Race\"}],\"OrderBy\":[{\"Direction\":2,\"Expression\":{\"Measure\":{\"Expression\":{\"SourceRef\":{\"Source\":\"m\"}},\"Property\":\"Total Black\"}}}]},\"drillFilterOtherVisuals\":true,\"hasDefaultSort\":true,\"objects\":{\"dataPoint\":[{\"properties\":{\"fill\":{\"solid\":{\"color\":{\"expr\":{\"ThemeDataColor\":{\"ColorId\":1,\"Percent\":0.4}}}}}},\"selector\":{\"metadata\":\"Measure Table.Total Black\"}},{\"properties\":{\"fill\":{\"solid\":{\"color\":{\"expr\":{\"ThemeDataColor\":{\"ColorId\":2,\"Percent\":0}}}}}},\"selector\":{\"metadata\":\"Measure Table.Total White\"}},{\"properties\":{\"fill\":{\"solid\":{\"color\":{\"expr\":{\"ThemeDataColor\":{\"ColorId\":8,\"Percent\":0}}}}}},\"selector\":{\"metadata\":\"Measure Table.Total Other Race\"}}]}}}",
          "filters": "[]",
          "height": 296.18,
          "width": 351.03,
          "x": 929.29,
          "y": 405.88,
          "z": 6000.00
        }
      ],
      "width": 1280.00
    }
  ]
}